mvtk/__init__.py
mvtk/credibility.py
mvtk/interprenet.py
mvtk/metrics.py
mvtk/sobol.py
mvtk/thresholding.py
mvtk/version.py
mvtk/bias_variance/__init__.py
mvtk/bias_variance/bias_variance.py
mvtk/bias_variance/bias_variance_parallel.py
mvtk/bias_variance/estimators/__init__.py
mvtk/bias_variance/estimators/estimator_wrapper.py
mvtk/bias_variance/estimators/pytorch_estimator_wrapper.py
mvtk/bias_variance/estimators/sklearn_estimator_wrapper.py
mvtk/bias_variance/estimators/tensorflow_estimator_wrapper.py
mvtk/supervisor/__init__.py
mvtk/supervisor/processing.py
mvtk/supervisor/utils.py
mvtk/supervisor/divergence/__init__.py
mvtk/supervisor/divergence/generators.py
mvtk/supervisor/divergence/metrics.py
mvtk/supervisor/divergence/nn.py
mvtk/supervisor/divergence/utils.py
mvtk-0.2.0.dist-info/LICENSE
mvtk-0.2.0.dist-info/METADATA
mvtk-0.2.0.dist-info/WHEEL
mvtk-0.2.0.dist-info/top_level.txt
mvtk-0.2.0.dist-info/RECORD
