Metadata-Version: 2.1
Name: mvtk
Version: 0.2.0
Summary: Model validation toolkit
Home-page: https://finraos.github.io/model-validation-toolkit/
Author: Alex Eftimiades
Author-email: alexeftimiades@gmail.com
License: Apache-2.0
Project-URL: Bug Tracker, https://github.com/FINRAOS/model-validation-toolkit/issues
Classifier: Programming Language :: Python :: 3
Classifier: License :: OSI Approved :: Apache Software License
Classifier: Operating System :: MacOS
Classifier: Operating System :: POSIX :: Linux
License-File: LICENSE
Requires-Dist: jax <=0.4.16,>=0.2.8
Requires-Dist: public >=2020.12.3
Requires-Dist: fastcore >=1.3.25
Requires-Dist: jaxlib <=0.4.16,>=0.1.23
Requires-Dist: scikit-learn
Requires-Dist: numpy
Requires-Dist: matplotlib
Requires-Dist: scipy
Requires-Dist: seaborn
Requires-Dist: pandas >=0.23.4
Requires-Dist: tqdm
Requires-Dist: ray
Provides-Extra: doc
Requires-Dist: nbsphinx ; extra == 'doc'
Requires-Dist: sphinx ; extra == 'doc'
Requires-Dist: sphinx-rtd-theme ; extra == 'doc'
Requires-Dist: sphinxcontrib-bibtex ; extra == 'doc'
Requires-Dist: imageio ; extra == 'doc'
Requires-Dist: myst-parser ; extra == 'doc'
Requires-Dist: ipykernel ; extra == 'doc'
Requires-Dist: torch ; extra == 'doc'
Requires-Dist: tensorflow ; extra == 'doc'
Provides-Extra: pytorch
Requires-Dist: torch ; extra == 'pytorch'
Provides-Extra: tensorflow
Requires-Dist: tensorflow ; extra == 'tensorflow'
